nprinter.py
nprinter-1.1.1.dist-info/METADATA
nprinter-1.1.1.dist-info/WHEEL
nprinter-1.1.1.dist-info/top_level.txt
nprinter-1.1.1.dist-info/RECORD
