Metadata-Version: 2.1
Name: nprinter
Version: 1.1.1
Summary: A simple level-based printer for nested lists
Home-page: http://www.nolinearpath.com
Author: nolinearpath
Author-email: donaldteghen@gmail.com
